{"0":{"id":1,"Any":2017,"Trimestre":1,"Codi_Districte":1,"Nom_Districte":"Ciutat Vella","Codi_Barri":1,"Nom_Barri":"el Raval","Lloguer_mitja":"Lloguer mitj\u00e0 mensual (Euros\/mes)","Preu":"734.99","created_at":"2022-06-07T11:28:56.000000Z","updated_at":"2022-06-07T11:28:56.000000Z"},"73":{"id":74,"Any":2017,"Trimestre":2,"Codi_Districte":1,"Nom_Districte":"Ciutat Vella","Codi_Barri":1,"Nom_Barri":"el Raval","Lloguer_mitja":"Lloguer mitj\u00e0 mensual (Euros\/mes)","Preu":"714.29","created_at":"2022-06-07T11:28:56.000000Z","updated_at":"2022-06-07T11:28:56.000000Z"},"146":{"id":147,"Any":2017,"Trimestre":3,"Codi_Districte":1,"Nom_Districte":"Ciutat Vella","Codi_Barri":1,"Nom_Barri":"el Raval","Lloguer_mitja":"Lloguer mitj\u00e0 mensual (Euros\/mes)","Preu":"764.85","created_at":"2022-06-07T11:28:57.000000Z","updated_at":"2022-06-07T11:28:57.000000Z"},"219":{"id":220,"Any":2017,"Trimestre":4,"Codi_Districte":1,"Nom_Districte":"Ciutat Vella","Codi_Barri":1,"Nom_Barri":"el Raval","Lloguer_mitja":"Lloguer mitj\u00e0 mensual (Euros\/mes)","Preu":"776.73","created_at":"2022-06-07T11:28:57.000000Z","updated_at":"2022-06-07T11:28:57.000000Z"},"292":{"id":293,"Any":2017,"Trimestre":1,"Codi_Districte":1,"Nom_Districte":"Ciutat Vella","Codi_Barri":1,"Nom_Barri":"el Raval","Lloguer_mitja":"Lloguer mitj\u00e0 per superf\u00edcie (Euros\/m2 mes)","Preu":"13.5","created_at":"2022-06-07T11:28:57.000000Z","updated_at":"2022-06-07T11:28:57.000000Z"},"365":{"id":366,"Any":2017,"Trimestre":2,"Codi_Districte":1,"Nom_Districte":"Ciutat Vella","Codi_Barri":1,"Nom_Barri":"el Raval","Lloguer_mitja":"Lloguer mitj\u00e0 per superf\u00edcie (Euros\/m2 mes)","Preu":"13.69","created_at":"2022-06-07T11:28:57.000000Z","updated_at":"2022-06-07T11:28:57.000000Z"},"438":{"id":439,"Any":2017,"Trimestre":3,"Codi_Districte":1,"Nom_Districte":"Ciutat Vella","Codi_Barri":1,"Nom_Barri":"el Raval","Lloguer_mitja":"Lloguer mitj\u00e0 per superf\u00edcie (Euros\/m2 mes)","Preu":"13.97","created_at":"2022-06-07T11:28:57.000000Z","updated_at":"2022-06-07T11:28:57.000000Z"},"511":{"id":512,"Any":2017,"Trimestre":4,"Codi_Districte":1,"Nom_Districte":"Ciutat Vella","Codi_Barri":1,"Nom_Barri":"el Raval","Lloguer_mitja":"Lloguer mitj\u00e0 per superf\u00edcie (Euros\/m2 mes)","Preu":"14.42","created_at":"2022-06-07T11:28:57.000000Z","updated_at":"2022-06-07T11:28:57.000000Z"},"584":{"id":585,"Any":2016,"Trimestre":1,"Codi_Districte":1,"Nom_Districte":"Ciutat Vella","Codi_Barri":1,"Nom_Barri":"el Raval","Lloguer_mitja":"Lloguer mitj\u00e0 mensual (Euros\/mes)","Preu":"624.42","created_at":"2022-06-07T11:28:57.000000Z","updated_at":"2022-06-07T11:28:57.000000Z"},"657":{"id":658,"Any":2016,"Trimestre":2,"Codi_Districte":1,"Nom_Districte":"Ciutat Vella","Codi_Barri":1,"Nom_Barri":"el Raval","Lloguer_mitja":"Lloguer mitj\u00e0 mensual (Euros\/mes)","Preu":"662.28","created_at":"2022-06-07T11:28:57.000000Z","updated_at":"2022-06-07T11:28:57.000000Z"},"730":{"id":731,"Any":2016,"Trimestre":3,"Codi_Districte":1,"Nom_Districte":"Ciutat Vella","Codi_Barri":1,"Nom_Barri":"el Raval","Lloguer_mitja":"Lloguer mitj\u00e0 mensual (Euros\/mes)","Preu":"666.17","created_at":"2022-06-07T11:28:58.000000Z","updated_at":"2022-06-07T11:28:58.000000Z"},"803":{"id":804,"Any":2016,"Trimestre":4,"Codi_Districte":1,"Nom_Districte":"Ciutat Vella","Codi_Barri":1,"Nom_Barri":"el Raval","Lloguer_mitja":"Lloguer mitj\u00e0 mensual (Euros\/mes)","Preu":"716.7","created_at":"2022-06-07T11:28:58.000000Z","updated_at":"2022-06-07T11:28:58.000000Z"},"876":{"id":877,"Any":2016,"Trimestre":1,"Codi_Districte":1,"Nom_Districte":"Ciutat Vella","Codi_Barri":1,"Nom_Barri":"el Raval","Lloguer_mitja":"Lloguer mitj\u00e0 per superf\u00edcie (Euros\/m2 mes)","Preu":"11.65","created_at":"2022-06-07T11:28:58.000000Z","updated_at":"2022-06-07T11:28:58.000000Z"},"949":{"id":950,"Any":2016,"Trimestre":2,"Codi_Districte":1,"Nom_Districte":"Ciutat Vella","Codi_Barri":1,"Nom_Barri":"el Raval","Lloguer_mitja":"Lloguer mitj\u00e0 per superf\u00edcie (Euros\/m2 mes)","Preu":"11.78","created_at":"2022-06-07T11:28:58.000000Z","updated_at":"2022-06-07T11:28:58.000000Z"},"1022":{"id":1023,"Any":2016,"Trimestre":3,"Codi_Districte":1,"Nom_Districte":"Ciutat Vella","Codi_Barri":1,"Nom_Barri":"el Raval","Lloguer_mitja":"Lloguer mitj\u00e0 per superf\u00edcie (Euros\/m2 mes)","Preu":"12.48","created_at":"2022-06-07T11:28:58.000000Z","updated_at":"2022-06-07T11:28:58.000000Z"},"1095":{"id":1096,"Any":2016,"Trimestre":4,"Codi_Districte":1,"Nom_Districte":"Ciutat Vella","Codi_Barri":1,"Nom_Barri":"el Raval","Lloguer_mitja":"Lloguer mitj\u00e0 per superf\u00edcie (Euros\/m2 mes)","Preu":"13.17","created_at":"2022-06-07T11:28:58.000000Z","updated_at":"2022-06-07T11:28:58.000000Z"},"1168":{"id":1169,"Any":2015,"Trimestre":1,"Codi_Districte":1,"Nom_Districte":"Ciutat Vella","Codi_Barri":1,"Nom_Barri":"el Raval","Lloguer_mitja":"Lloguer mitj\u00e0 mensual (Euros\/mes)","Preu":"601.31","created_at":"2022-06-07T11:28:58.000000Z","updated_at":"2022-06-07T11:28:58.000000Z"},"1241":{"id":1242,"Any":2015,"Trimestre":2,"Codi_Districte":1,"Nom_Districte":"Ciutat Vella","Codi_Barri":1,"Nom_Barri":"el Raval","Lloguer_mitja":"Lloguer mitj\u00e0 mensual (Euros\/mes)","Preu":"598.91","created_at":"2022-06-07T11:28:58.000000Z","updated_at":"2022-06-07T11:28:58.000000Z"},"1314":{"id":1315,"Any":2015,"Trimestre":3,"Codi_Districte":1,"Nom_Districte":"Ciutat Vella","Codi_Barri":1,"Nom_Barri":"el Raval","Lloguer_mitja":"Lloguer mitj\u00e0 mensual (Euros\/mes)","Preu":"654","created_at":"2022-06-07T11:28:58.000000Z","updated_at":"2022-06-07T11:28:58.000000Z"},"1387":{"id":1388,"Any":2015,"Trimestre":4,"Codi_Districte":1,"Nom_Districte":"Ciutat Vella","Codi_Barri":1,"Nom_Barri":"el Raval","Lloguer_mitja":"Lloguer mitj\u00e0 mensual (Euros\/mes)","Preu":"644.73","created_at":"2022-06-07T11:28:59.000000Z","updated_at":"2022-06-07T11:28:59.000000Z"},"1460":{"id":1461,"Any":2015,"Trimestre":1,"Codi_Districte":1,"Nom_Districte":"Ciutat Vella","Codi_Barri":1,"Nom_Barri":"el Raval","Lloguer_mitja":"Lloguer mitj\u00e0 per superf\u00edcie (Euros\/m2 mes)","Preu":"10.6","created_at":"2022-06-07T11:28:59.000000Z","updated_at":"2022-06-07T11:28:59.000000Z"},"1533":{"id":1534,"Any":2015,"Trimestre":2,"Codi_Districte":1,"Nom_Districte":"Ciutat Vella","Codi_Barri":1,"Nom_Barri":"el Raval","Lloguer_mitja":"Lloguer mitj\u00e0 per superf\u00edcie (Euros\/m2 mes)","Preu":"10.92","created_at":"2022-06-07T11:28:59.000000Z","updated_at":"2022-06-07T11:28:59.000000Z"},"1606":{"id":1607,"Any":2015,"Trimestre":3,"Codi_Districte":1,"Nom_Districte":"Ciutat Vella","Codi_Barri":1,"Nom_Barri":"el Raval","Lloguer_mitja":"Lloguer mitj\u00e0 per superf\u00edcie (Euros\/m2 mes)","Preu":"11","created_at":"2022-06-07T11:28:59.000000Z","updated_at":"2022-06-07T11:28:59.000000Z"},"1679":{"id":1680,"Any":2015,"Trimestre":4,"Codi_Districte":1,"Nom_Districte":"Ciutat Vella","Codi_Barri":1,"Nom_Barri":"el Raval","Lloguer_mitja":"Lloguer mitj\u00e0 per superf\u00edcie (Euros\/m2 mes)","Preu":"11.47","created_at":"2022-06-07T11:28:59.000000Z","updated_at":"2022-06-07T11:28:59.000000Z"},"1752":{"id":1753,"Any":2014,"Trimestre":1,"Codi_Districte":1,"Nom_Districte":"Ciutat Vella","Codi_Barri":1,"Nom_Barri":"el Raval","Lloguer_mitja":"Lloguer mitj\u00e0 mensual (Euros\/mes)","Preu":"589.55","created_at":"2022-06-07T11:28:59.000000Z","updated_at":"2022-06-07T11:28:59.000000Z"},"1825":{"id":1826,"Any":2014,"Trimestre":2,"Codi_Districte":1,"Nom_Districte":"Ciutat Vella","Codi_Barri":1,"Nom_Barri":"el Raval","Lloguer_mitja":"Lloguer mitj\u00e0 mensual (Euros\/mes)","Preu":"550.63","created_at":"2022-06-07T11:28:59.000000Z","updated_at":"2022-06-07T11:28:59.000000Z"},"1898":{"id":1899,"Any":2014,"Trimestre":3,"Codi_Districte":1,"Nom_Districte":"Ciutat Vella","Codi_Barri":1,"Nom_Barri":"el Raval","Lloguer_mitja":"Lloguer mitj\u00e0 mensual (Euros\/mes)","Preu":"576.45","created_at":"2022-06-07T11:28:59.000000Z","updated_at":"2022-06-07T11:28:59.000000Z"},"1971":{"id":1972,"Any":2014,"Trimestre":4,"Codi_Districte":1,"Nom_Districte":"Ciutat Vella","Codi_Barri":1,"Nom_Barri":"el Raval","Lloguer_mitja":"Lloguer mitj\u00e0 mensual (Euros\/mes)","Preu":"597","created_at":"2022-06-07T11:29:00.000000Z","updated_at":"2022-06-07T11:29:00.000000Z"},"2044":{"id":2045,"Any":2014,"Trimestre":1,"Codi_Districte":1,"Nom_Districte":"Ciutat Vella","Codi_Barri":1,"Nom_Barri":"el Raval","Lloguer_mitja":"Lloguer mitj\u00e0 per superf\u00edcie (Euros\/m2 mes)","Preu":"10.76","created_at":"2022-06-07T11:29:00.000000Z","updated_at":"2022-06-07T11:29:00.000000Z"},"2117":{"id":2118,"Any":2014,"Trimestre":2,"Codi_Districte":1,"Nom_Districte":"Ciutat Vella","Codi_Barri":1,"Nom_Barri":"el Raval","Lloguer_mitja":"Lloguer mitj\u00e0 per superf\u00edcie (Euros\/m2 mes)","Preu":"10.52","created_at":"2022-06-07T11:29:00.000000Z","updated_at":"2022-06-07T11:29:00.000000Z"},"2190":{"id":2191,"Any":2014,"Trimestre":3,"Codi_Districte":1,"Nom_Districte":"Ciutat Vella","Codi_Barri":1,"Nom_Barri":"el Raval","Lloguer_mitja":"Lloguer mitj\u00e0 per superf\u00edcie (Euros\/m2 mes)","Preu":"9.84","created_at":"2022-06-07T11:29:00.000000Z","updated_at":"2022-06-07T11:29:00.000000Z"},"2263":{"id":2264,"Any":2014,"Trimestre":4,"Codi_Districte":1,"Nom_Districte":"Ciutat Vella","Codi_Barri":1,"Nom_Barri":"el Raval","Lloguer_mitja":"Lloguer mitj\u00e0 per superf\u00edcie (Euros\/m2 mes)","Preu":"10.81","created_at":"2022-06-07T11:29:00.000000Z","updated_at":"2022-06-07T11:29:00.000000Z"},"2336":{"id":2337,"Any":2019,"Trimestre":1,"Codi_Districte":1,"Nom_Districte":"Ciutat Vella","Codi_Barri":1,"Nom_Barri":"el Raval","Lloguer_mitja":"Lloguer mitj\u00e0 mensual (Euros\/mes)","Preu":"822.6","created_at":"2022-06-07T11:29:00.000000Z","updated_at":"2022-06-07T11:29:00.000000Z"},"2409":{"id":2410,"Any":2019,"Trimestre":1,"Codi_Districte":1,"Nom_Districte":"Ciutat Vella","Codi_Barri":1,"Nom_Barri":"el Raval","Lloguer_mitja":"Lloguer mitj\u00e0 per superf\u00edcie (Euros\/m2 mes)","Preu":"14.1","created_at":"2022-06-07T11:29:00.000000Z","updated_at":"2022-06-07T11:29:00.000000Z"},"2482":{"id":2483,"Any":2019,"Trimestre":2,"Codi_Districte":1,"Nom_Districte":"Ciutat Vella","Codi_Barri":1,"Nom_Barri":"el Raval","Lloguer_mitja":"Lloguer mitj\u00e0 mensual (Euros\/mes)","Preu":"867.0","created_at":"2022-06-07T11:29:00.000000Z","updated_at":"2022-06-07T11:29:00.000000Z"},"2555":{"id":2556,"Any":2019,"Trimestre":2,"Codi_Districte":1,"Nom_Districte":"Ciutat Vella","Codi_Barri":1,"Nom_Barri":"el Raval","Lloguer_mitja":"Lloguer mitj\u00e0 per superf\u00edcie (Euros\/m2 mes)","Preu":"14.5","created_at":"2022-06-07T11:29:00.000000Z","updated_at":"2022-06-07T11:29:00.000000Z"},"2628":{"id":2629,"Any":2019,"Trimestre":3,"Codi_Districte":1,"Nom_Districte":"Ciutat Vella","Codi_Barri":1,"Nom_Barri":"el Raval","Lloguer_mitja":"Lloguer mitj\u00e0 mensual (Euros\/mes)","Preu":"869.1","created_at":"2022-06-07T11:29:01.000000Z","updated_at":"2022-06-07T11:29:01.000000Z"},"2701":{"id":2702,"Any":2019,"Trimestre":3,"Codi_Districte":1,"Nom_Districte":"Ciutat Vella","Codi_Barri":1,"Nom_Barri":"el Raval","Lloguer_mitja":"Lloguer mitj\u00e0 per superf\u00edcie (Euros\/m2 mes)","Preu":"14.7","created_at":"2022-06-07T11:29:01.000000Z","updated_at":"2022-06-07T11:29:01.000000Z"},"2774":{"id":2775,"Any":2019,"Trimestre":4,"Codi_Districte":1,"Nom_Districte":"Ciutat Vella","Codi_Barri":1,"Nom_Barri":"el Raval","Lloguer_mitja":"Lloguer mitj\u00e0 mensual (Euros\/mes)","Preu":"844.9","created_at":"2022-06-07T11:29:01.000000Z","updated_at":"2022-06-07T11:29:01.000000Z"},"2847":{"id":2848,"Any":2019,"Trimestre":4,"Codi_Districte":1,"Nom_Districte":"Ciutat Vella","Codi_Barri":1,"Nom_Barri":"el Raval","Lloguer_mitja":"Lloguer mitj\u00e0 per superf\u00edcie (Euros\/m2 mes)","Preu":"14.0","created_at":"2022-06-07T11:29:01.000000Z","updated_at":"2022-06-07T11:29:01.000000Z"},"2992":{"id":2993,"Any":2018,"Trimestre":2,"Codi_Districte":1,"Nom_Districte":"Ciutat Vella","Codi_Barri":1,"Nom_Barri":"el Raval","Lloguer_mitja":"Lloguer mitj\u00e0 mensual (Euros\/mes)","Preu":"820.88","created_at":"2022-06-07T11:29:01.000000Z","updated_at":"2022-06-07T11:29:01.000000Z"},"3065":{"id":3066,"Any":2018,"Trimestre":3,"Codi_Districte":1,"Nom_Districte":"Ciutat Vella","Codi_Barri":1,"Nom_Barri":"el Raval","Lloguer_mitja":"Lloguer mitj\u00e0 mensual (Euros\/mes)","Preu":"849.32","created_at":"2022-06-07T11:29:01.000000Z","updated_at":"2022-06-07T11:29:01.000000Z"},"3138":{"id":3139,"Any":2018,"Trimestre":4,"Codi_Districte":1,"Nom_Districte":"Ciutat Vella","Codi_Barri":1,"Nom_Barri":"el Raval","Lloguer_mitja":"Lloguer mitj\u00e0 mensual (Euros\/mes)","Preu":"827.27","created_at":"2022-06-07T11:29:01.000000Z","updated_at":"2022-06-07T11:29:01.000000Z"},"3211":{"id":3212,"Any":2018,"Trimestre":1,"Codi_Districte":1,"Nom_Districte":"Ciutat Vella","Codi_Barri":1,"Nom_Barri":"el Raval","Lloguer_mitja":"Lloguer mitj\u00e0 per superf\u00edcie (Euros\/m2 mes)","Preu":"13.74","created_at":"2022-06-07T11:29:02.000000Z","updated_at":"2022-06-07T11:29:02.000000Z"},"3284":{"id":3285,"Any":2018,"Trimestre":2,"Codi_Districte":1,"Nom_Districte":"Ciutat Vella","Codi_Barri":1,"Nom_Barri":"el Raval","Lloguer_mitja":"Lloguer mitj\u00e0 per superf\u00edcie (Euros\/m2 mes)","Preu":"14.14","created_at":"2022-06-07T11:29:02.000000Z","updated_at":"2022-06-07T11:29:02.000000Z"},"3357":{"id":3358,"Any":2018,"Trimestre":3,"Codi_Districte":1,"Nom_Districte":"Ciutat Vella","Codi_Barri":1,"Nom_Barri":"el Raval","Lloguer_mitja":"Lloguer mitj\u00e0 per superf\u00edcie (Euros\/m2 mes)","Preu":"14.12","created_at":"2022-06-07T11:29:02.000000Z","updated_at":"2022-06-07T11:29:02.000000Z"},"3430":{"id":3431,"Any":2018,"Trimestre":4,"Codi_Districte":1,"Nom_Districte":"Ciutat Vella","Codi_Barri":1,"Nom_Barri":"el Raval","Lloguer_mitja":"Lloguer mitj\u00e0 per superf\u00edcie (Euros\/m2 mes)","Preu":"14.07","created_at":"2022-06-07T11:29:02.000000Z","updated_at":"2022-06-07T11:29:02.000000Z"}}